{
  "produtos": [
    {
      "id": "c77b",
      "nome": "Game Boy Advance",
      "preco": "250.00",
      "imagem": "https://upload.wikimedia.org/wikipedia/commons/7/7d/Nintendo-Game-Boy-Advance-Purple-FL.jpg"
    },
    {
      "id": "14af",
      "nome": "Game Boy Advance",
      "preco": "250.00",
      "imagem": "https://upload.wikimedia.org/wikipedia/commons/7/7d/Nintendo-Game-Boy-Advance-Purple-FL.jpg"
    },
    {
      "id": "e9ca",
      "nome": "Game Boy Advance",
      "preco": "250.00",
      "imagem": "https://upload.wikimedia.org/wikipedia/commons/7/7d/Nintendo-Game-Boy-Advance-Purple-FL.jpg"
    },
    {
      "id": "28d4",
      "nome": "Game Boy Advance",
      "preco": "250.00",
      "imagem": "https://encrypted-tbn0.gstatic.com/images?q=tbn:ANd9GcQzb2aszvzl3lpfaqdyQhiVPT98TdZNnPPjldlOE_Sl_g&s"
    },
    {
      "id": "9db8",
      "nome": "Pietro",
      "preco": "250.00",
      "imagem": "https://encrypted-tbn0.gstatic.com/images?q=tbn:ANd9GcQzb2aszvzl3lpfaqdyQhiVPT98TdZNnPPjldlOE_Sl_g&s"
    }
  ]
}